{
  "title": "What kinda burger you want?",
  "text": "There's gonna be some good shit, but I need to know some stuff about how you like your burger",
  "section": [
    {
      "title": "Do you eat kosher?",
      "content": "I will not put cheese on your burger. You're still going to hell though.",
      "icon": "notes.svg"
    },
    {
      "title": "Are you vegeterian?",
      "content": "I can get you some plant based stuff. That might suck ass though.",
      "icon": "notes.svg"
    }
  ]
}
